probabilistic_loss_functions/__init__.py
probabilistic_loss_functions/losses.py
probabilistic_loss_functions-0.1.1.dist-info/WHEEL
probabilistic_loss_functions-0.1.1.dist-info/METADATA
probabilistic_loss_functions-0.1.1.dist-info/RECORD
