Metadata-Version: 2.1
Name: probabilistic-loss-functions
Version: 0.1.1
Summary: 
Author: ninpnin
Author-email: vainoyrjanainen@icloud.com
Requires-Python: >=3.9,<4.0
Classifier: Programming Language :: Python :: 3
Classifier: Programming Language :: Python :: 3.10
Classifier: Programming Language :: Python :: 3.9
Requires-Dist: tensorflow-probability (>=0.12.0,<0.13.0)
